setup.cfg
setup.py
bucket_list.egg-info/PKG-INFO
bucket_list.egg-info/SOURCES.txt
bucket_list.egg-info/dependency_links.txt
bucket_list.egg-info/entry_points.txt
bucket_list.egg-info/requires.txt
bucket_list.egg-info/top_level.txt
bucketlist/__init__.py
bucketlist/cmdline.py
bucketlist/configio.py
bucketlist/decorators.py
bucketlist/defaults.py
bucketlist/entities.py
bucketlist/errors.py
bucketlist/utils.py
bucketlist/commands/__init__.py
bucketlist/commands/add.py
bucketlist/commands/backup.py
bucketlist/commands/clean.py
bucketlist/commands/config.py
bucketlist/commands/init.py
bucketlist/commands/mark.py
bucketlist/commands/restore.py
bucketlist/commands/view.py
bucketlist/providers/__init__.py
bucketlist/providers/localfs/__init__.py
bucketlist/providers/localfs/localfs.py
bucketlist/providers/localfs/localfs_api.py
bucketlist/providers/wunderlist/__init__.py
bucketlist/providers/wunderlist/wrequests.py
bucketlist/providers/wunderlist/wunderlist.py
bucketlist/providers/wunderlist/wunderlist_api.py
bucketlist/render/__init__.py
bucketlist/render/tables.py