Metadata-Version: 1.1
Name: bucket-list
Version: 0.3.4
Summary: Command line interface for managining bucketlist
Home-page: https://github.com/arpitbbhayani/bucket-list
Author: Arpit Bhayani
Author-email: arpit.b.bhayani@gmail.com
License: UNKNOWN
Download-URL: https://github.com/arpitbbhayani/bucket-list
Keywords: bucket list,cli
Platform: UNKNOWN
